rashell/__init__.py
rashell/exceptions.py
rashell/grammar_files/rashell_grammar.tx
rashell/grammar_files/rashell_program_grammar.tx
rashell/rashell.py
rashell/relational_engine.py
rashell/relational_model.py
rashell-0.2.7.dist-info/entry_points.txt
rashell-0.2.7.dist-info/LICENSE.txt
rashell-0.2.7.dist-info/WHEEL
rashell-0.2.7.dist-info/METADATA
rashell-0.2.7.dist-info/RECORD
