Metadata-Version: 2.1
Name: rashell
Version: 0.2.7
Summary: rashell is a Relational Algebra Shell. It provides a DSL to define and populate relational models and a REPL interface to query relational models using relational algebra operations. This tool is intended for educational use only, to illustrate in a more interactive way the underlying concepts of relational databases
Home-page: https://github.com/skebir/rashell
License: MIT
Keywords: Relational Algebra,Shell,CLI,Database
Author: Salim Kebir
Author-email: s.kebir@esti-annaba.dz
Requires-Python: >=3.8,<4.0
Classifier: License :: OSI Approved :: MIT License
Classifier: Programming Language :: Python :: 3
Classifier: Programming Language :: Python :: 3.10
Classifier: Programming Language :: Python :: 3.8
Classifier: Programming Language :: Python :: 3.9
Classifier: Topic :: Education :: Computer Aided Instruction (CAI)
Requires-Dist: prompt-toolkit (>=3.0.29,<4.0.0)
Requires-Dist: rich (>=12.3.0,<13.0.0)
Requires-Dist: textX (>=3.0.0,<4.0.0)
